CHANGES
LICENSE
MANIFEST.in
README
setup.py
stamps/__init__.py
stamps/config.py
stamps/services.py
stamps/tests.py
stamps.py.egg-info/PKG-INFO
stamps.py.egg-info/SOURCES.txt
stamps.py.egg-info/dependency_links.txt
stamps.py.egg-info/requires.txt
stamps.py.egg-info/top_level.txt
stamps/wsdls/stamps_v49.test.wsdl
stamps/wsdls/stamps_v49.wsdl