Metadata-Version: 1.0
Name: stamps.py
Version: 0.8
Summary: Stamps.com API for Python.
Home-page: http://github.com/jzempel/stamps
Author: Jonathan Zempel
Author-email: jzempel@gmail.com
License: BSD
Platform: UNKNOWN
